{"abyssinian":"Abyssinian","american-bobtail":"American Bobtail","american-curl":"American Curl","american-shorthair":"American Shorthair","american-wirehair":"American Wirehair","balinese":"Balinese","bengal":"Bengal","birman":"Birman","bombay":"Bombay","british-shorthair":"British Shorthair","burmese":"Burmese","burmilla":"Burmilla","calico":"Calico","chartreux":"Chartreux","chausie":"Chausie","cornish-rex":"Cornish Rex","cymric":"Cymric","devon-rex":"Devon Rex","domestic-long-hair-cat-breed-profile":"Domestic Long Hair","domestic-medium-hair-cat-breed-profile":"Domestic Medium Hair","domestic-shorthair":"Domestic Shorthair","egyptian-mau":"Egyptian Mau","exotic-shorthair":"Exotic Shorthair","havana-brown":"Havana","himalayan":"Himalayan","japanese-bobtail":"Japanese Bobtail","javanese":"Javanese","korat":"Korat","laperm":"LaPerm","maine-coon":"Maine Coon","manx":"Manx","munchkin":"Munchkin","nebelung":"Nebelung","norwegian-forest-cat":"Norwegian Forest Cat","ocicat":"Ocicat","oriental":"Oriental Short Hair","persian":"Persian","pixiebob":"Pixiebob","ragamuffin":"Ragamuffin","ragdoll":"Ragdoll","russian-blue":"Russian Blue","scottish-fold":"Scottish Fold","selkirk-rex":"Selkirk Rex","siamese":"Siamese","siberian":"Siberian","singapura":"Singapura","snowshoe":"Snowshoe","somali":"Somali","sphynx":"Sphynx \/ Hairless Cat","tabby":"Tabby","tonkinese":"Tonkinese","tortoiseshell":"Tortoiseshell","toyger":"Toyger","turkish-angora":"Turkish Angora","turkish-van":"Turkish Van","tuxedo":"Tuxedo","york-chocolate":"York Chocolate"}